Workbook

Sheet 0. Document Details
B2: Demand Forecast Tool | F2: How to use this tool
B4: Document details | F4: Step 1. Estimate your demand function
B5: Document owner | C5: Joe Bloggs | F5: First, we need to estimate how changes in the price of our product result in changes in units sold. This is a difficult exercise but the most common methods to estimate this include testing different prices across geographies, using surveys, observing competing products, or speaking to subject matter experts. The goal is to get as many "price-units sold" combinations as possible.
B6: Document version | C6: 1.0
B7: Last updated | C7: =TODAY() -> 45423
B9: Cell Reference | F9: Step 2. Input the price-sales data into the "1. LOBF Estimator" tab
B10: Grey | C10: Title / Text (Do not overwrite) | F10: Next, type the price and units sold data in the input fields in the next tab:
B11: White | C11: Calculation (Do not overwrite)
B12: Blue | C12: Input (Overwrite)
F17: Step 3. Determine the most appropriate demand function
F18: This tool will automatically fit a linear, exponential, power and logarithmic curve to your data, and determine which is the best fitting function. It will also calculate the coefficients for each function. You simply need to review call D31 to determine the best fitting function:
F36: Step 4. Forecast demand in the appropriate tab
F37: Once you have determined the best fitting function, navigate to the associated tab. The function's coefficients will already be updated in this tab. Therefore, to forecast and calculate your demand curve, you simply need to change the price values in the input cells and update the cost inputs (if needed):

Sheet 1. LOBF Estimator
B2: INPUTS
B4: Actuals | D4: 1 | E4: =D4+1 -> 2 | F4: =E4+1 -> 3 | G4: =F4+1 -> 4 | H4: =G4+1 -> 5 | I4: =H4+1 -> 6 | J4: =I4+1 -> 7
B5: Price | C5: $ | D5: 10 | E5: =D5+5 -> 15 | F5: =E5+5 -> 20 | G5: =F5+5 -> 25 | H5: =G5+5 -> 30 | I5: =H5+5 -> 35 | J5: =I5+5 -> 40
B6: Demand (Units) | C6: # | D6: 31000 | E6: 20000 | F6: 15000 | G6: 9500 | H6: 6500 | I6: 4500 | J6: 3000
B9: CALCULATIONS
B11: Linear | D11: =D4 -> 1 | E11: =E4 -> 2 | F11: =F4 -> 3 | G11: =G4 -> 4 | H11: =H4 -> 5 | I11: =I4 -> 6 | J11: =J4 -> 7 | L11: Calculations
B12: Price | C12: $ | D12: =D5 -> 10 | E12: =E5 -> 15 | F12: =F5 -> 20 | G12: =G5 -> 25 | H12: =H5 -> 30 | I12: =I5 -> 35 | J12: =J5 -> 40 | L12: m | M12: b | O12: std error
B13: Demand (Units) | C13: # | D13: =($L$13*D12)+$M$13 -> 26017.857 | E13: =($L$13*E12)+$M$13 -> 21607.143 | F13: =($L$13*F12)+$M$13 -> 17196.429 | G13: =($L$13*G12)+$M$13 -> 12785.714 | H13: =($L$13*H12)+$M$13 -> 8375 | I13: =($L$13*I12)+$M$13 -> 3964.2857 | J13: =($L$13*J12)+$M$13 -> -446.42857 | L13: {=LINEST(D6:J6,D5:J5,TRUE,FALSE)} -> -882.14286 | M13: 34839.286 | O13: =STEYX($D$6:$J$6,D13:J13) -> 3426.5247
B15: Exponential | D15: =D11 -> 1 | E15: =E11 -> 2 | F15: =F11 -> 3 | G15: =G11 -> 4 | H15: =H11 -> 5 | I15: =I11 -> 6 | J15: =J11 -> 7 | L15: =L11 -> Calculations
B16: Price | C16: $ | D16: =D5 -> 10 | E16: =E5 -> 15 | F16: =F5 -> 20 | G16: =G5 -> 25 | H16: =H5 -> 30 | I16: =I5 -> 35 | J16: =J5 -> 40 | L16: b | M16: ln(a) | N16: a | O16: std error
B17: Demand (Units) | C17: # | D17: =$N$17*(EXP($L$17*D16)) -> 30756.965 | E17: =$N$17*(EXP($L$17*E16)) -> 20894.479 | F17: =$N$17*(EXP($L$17*F16)) -> 14194.484 | G17: =$N$17*(EXP($L$17*G16)) -> 9642.9001 | H17: =$N$17*(EXP($L$17*H16)) -> 6550.821 | I17: =$N$17*(EXP($L$17*I16)) -> 4450.2437 | J17: =$N$17*(EXP($L$17*J16)) -> 3023.2347 | L17: {=LINEST(LN(D6:J6),D5:J5,TRUE,FALSE)} -> -0.077326304 | M17: 11.107135 | N17: =EXP(M17) -> 66644.965 | O17: =STEYX($D$6:$J$6,D17:J17) -> 553.48588
B19: Power | D19: =D15 -> 1 | E19: =E15 -> 2 | F19: =F15 -> 3 | G19: =G15 -> 4 | H19: =H15 -> 5 | I19: =I15 -> 6 | J19: =J15 -> 7 | L19: =L15 -> Calculations
B20: Price | C20: $ | D20: =D5 -> 10 | E20: =E5 -> 15 | F20: =F5 -> 20 | G20: =G5 -> 25 | H20: =H5 -> 30 | I20: =I5 -> 35 | J20: =J5 -> 40 | L20: b | M20: ln(a) | N20: a | O20: std error
B21: Demand (Units) | C21: # | D21: =$N$21*(D20^$L$21) -> 37787.593 | E21: =$N$21*(E20^$L$21) -> 19261.927 | F21: =$N$21*(F20^$L$21) -> 11941.575 | G21: =$N$21*(G20^$L$21) -> 8241.4758 | H21: =$N$21*(H20^$L$21) -> 6087.1238 | I21: =$N$21*(I20^$L$21) -> 4711.4215 | J21: =$N$21*(J20^$L$21) -> 3773.7577 | L21: {=LINEST(LN(D6:J6),LN(D5:J5),TRUE,FALSE)} -> -1.6619195 | M21: 14.366447 | N21: =EXP(M21) -> 1734877 | O21: =STEYX($D$6:$J$6,D21:J21) -> 2282.4863
B23: Logarithmic | D23: =D19 -> 1 | E23: =E19 -> 2 | F23: =F19 -> 3 | G23: =G19 -> 4 | H23: =H19 -> 5 | I23: =I19 -> 6 | J23: =J19 -> 7 | L23: =L19 -> Calculations
B24: Price | C24: $ | D24: =D5 -> 10 | E24: =E5 -> 15 | F24: =F5 -> 20 | G24: =G5 -> 25 | H24: =H5 -> 30 | I24: =I5 -> 35 | J24: =J5 -> 40 | L24: a | M24: b | O24: std error
B25: Demand (Units) | C25: # | D25: =$L$25*LN(D24)+$M$25 -> 29390.279 | E25: =$L$25*LN(E24)+$M$25 -> 21197.77 | F25: =$L$25*LN(F24)+$M$25 -> 15385.093 | G25: =$L$25*LN(G24)+$M$25 -> 10876.43 | H25: =$L$25*LN(H24)+$M$25 -> 7192.5841 | I25: =$L$25*LN(I24)+$M$25 -> 4077.9368 | J25: =$L$25*LN(J24)+$M$25 -> 1379.9066 | L25: {=LINEST(D6:J6,LN(D5:J5),TRUE,FALSE)} -> -20205.213 | M25: 75914.501 | O25: =STEYX($D$6:$J$6,D25:J25) -> 1367.5689
B28: OUTPUTS | O28: `
B30: Best fitting line: | D30: {=INDEX(B11:B25,MATCH(MIN(O13,O17,O21,O25),O11:O25,0)-2,0)} -> Exponential
N39: \
G52: `

Sheet 2a. Linear LOBF
B2: Linear Line of Best Fit Pricing Model | L2: Equation
B3: Price | C3: $ | D3: ='1. LOBF Estimator'!D5 -> 10 | E3: ='1. LOBF Estimator'!E5 -> 15 | F3: ='1. LOBF Estimator'!F5 -> 20 | G3: ='1. LOBF Estimator'!G5 -> 25 | H3: ='1. LOBF Estimator'!H5 -> 30 | I3: ='1. LOBF Estimator'!I5 -> 35 | J3: ='1. LOBF Estimator'!J5 -> 40
B4: Demand (Units) | C4: # | D4: =IF($M$5*D3+$M$6<0,0,$M$5*D3+$M$6) -> 26017.857 | E4: =IF($M$5*E3+$M$6<0,0,$M$5*E3+$M$6) -> 21607.143 | F4: =IF($M$5*F3+$M$6<0,0,$M$5*F3+$M$6) -> 17196.429 | G4: =IF($M$5*G3+$M$6<0,0,$M$5*G3+$M$6) -> 12785.714 | H4: =IF($M$5*H3+$M$6<0,0,$M$5*H3+$M$6) -> 8375 | I4: =IF($M$5*I3+$M$6<0,0,$M$5*I3+$M$6) -> 3964.2857 | J4: =IF($M$5*J3+$M$6<0,0,$M$5*J3+$M$6) -> 0 | L4: Equation Inputs
B5: Revenue | D5: =D3*D4 -> 260178.57 | E5: =E3*E4 -> 324107.14 | F5: =F3*F4 -> 343928.57 | G5: =G3*G4 -> 319642.86 | H5: =H3*H4 -> 251250 | I5: =I3*I4 -> 138750 | J5: =J3*J4 -> 0 | L5: m | M5: ='1. LOBF Estimator'!L13 -> -882.14286
L6: b | M6: ='1. LOBF Estimator'!M13 -> 34839.286
G46: `

Sheet 2b. Exponential LOBF
B2: Exponential Line of Best Fit Pricing Model | L2: Equation
B3: Price | C3: $ | D3: ='1. LOBF Estimator'!D5 -> 10 | E3: ='1. LOBF Estimator'!E5 -> 15 | F3: ='1. LOBF Estimator'!F5 -> 20 | G3: ='1. LOBF Estimator'!G5 -> 25 | H3: ='1. LOBF Estimator'!H5 -> 30 | I3: ='1. LOBF Estimator'!I5 -> 35 | J3: ='1. LOBF Estimator'!J5 -> 40
B4: Demand (Units) | C4: # | D4: =IF($M$5*EXP($M$6*D3)<0,0,$M$5*EXP($M$6*D3)) -> 30756.965 | E4: =IF($M$5*EXP($M$6*E3)<0,0,$M$5*EXP($M$6*E3)) -> 20894.479 | F4: =IF($M$5*EXP($M$6*F3)<0,0,$M$5*EXP($M$6*F3)) -> 14194.484 | G4: =IF($M$5*EXP($M$6*G3)<0,0,$M$5*EXP($M$6*G3)) -> 9642.9001 | H4: =IF($M$5*EXP($M$6*H3)<0,0,$M$5*EXP($M$6*H3)) -> 6550.821 | I4: =IF($M$5*EXP($M$6*I3)<0,0,$M$5*EXP($M$6*I3)) -> 4450.2437 | J4: =IF($M$5*EXP($M$6*J3)<0,0,$M$5*EXP($M$6*J3)) -> 3023.2347 | L4: Equation Inputs
B5: Revenue | D5: =D3*D4 -> 307569.65 | E5: =E3*E4 -> 313417.18 | F5: =F3*F4 -> 283889.68 | G5: =G3*G4 -> 241072.5 | H5: =H3*H4 -> 196524.63 | I5: =I3*I4 -> 155758.53 | J5: =J3*J4 -> 120929.39 | L5: a | M5: ='1. LOBF Estimator'!N17 -> 66644.965
L6: b | M6: ='1. LOBF Estimator'!L17 -> -0.077326304
G46: `

Sheet 2c. Power LOBF
B2: Power Line of Best Fit Pricing Model | L2: Equation
B3: Price | C3: $ | D3: ='1. LOBF Estimator'!D5 -> 10 | E3: ='1. LOBF Estimator'!E5 -> 15 | F3: ='1. LOBF Estimator'!F5 -> 20 | G3: ='1. LOBF Estimator'!G5 -> 25 | H3: ='1. LOBF Estimator'!H5 -> 30 | I3: ='1. LOBF Estimator'!I5 -> 35 | J3: ='1. LOBF Estimator'!J5 -> 40
B4: Demand (Units) | C4: # | D4: =IF(($M$5*D3^$M$6)<0,0,($M$5*D3^$M$6)) -> 37787.593 | E4: =IF(($M$5*E3^$M$6)<0,0,($M$5*E3^$M$6)) -> 19261.927 | F4: =IF(($M$5*F3^$M$6)<0,0,($M$5*F3^$M$6)) -> 11941.575 | G4: =IF(($M$5*G3^$M$6)<0,0,($M$5*G3^$M$6)) -> 8241.4758 | H4: =IF(($M$5*H3^$M$6)<0,0,($M$5*H3^$M$6)) -> 6087.1238 | I4: =IF(($M$5*I3^$M$6)<0,0,($M$5*I3^$M$6)) -> 4711.4215 | J4: =IF(($M$5*J3^$M$6)<0,0,($M$5*J3^$M$6)) -> 3773.7577 | L4: Equation Inputs
B5: Revenue | D5: =D3*D4 -> 377875.93 | E5: =E3*E4 -> 288928.91 | F5: =F3*F4 -> 238831.51 | G5: =G3*G4 -> 206036.89 | H5: =H3*H4 -> 182613.71 | I5: =I3*I4 -> 164899.75 | J5: =J3*J4 -> 150950.31 | L5: a | M5: ='1. LOBF Estimator'!N21 -> 1734877
L6: b | M6: ='1. LOBF Estimator'!L21 -> -1.6619195
G46: `

Sheet 2d. Logarithmic LOBF
B2: Logarithmic Line of Best Fit Pricing Model | L2: Equation
B3: Price | C3: $ | D3: ='1. LOBF Estimator'!D5 -> 10 | E3: ='1. LOBF Estimator'!E5 -> 15 | F3: ='1. LOBF Estimator'!F5 -> 20 | G3: ='1. LOBF Estimator'!G5 -> 25 | H3: ='1. LOBF Estimator'!H5 -> 30 | I3: ='1. LOBF Estimator'!I5 -> 35 | J3: ='1. LOBF Estimator'!J5 -> 40
B4: Demand (Units) | C4: # | D4: =IF($M$5*LN(D3)+$M$6<0,0,$M$5*LN(D3)+$M$6) -> 29390.279 | E4: =IF($M$5*LN(E3)+$M$6<0,0,$M$5*LN(E3)+$M$6) -> 21197.77 | F4: =IF($M$5*LN(F3)+$M$6<0,0,$M$5*LN(F3)+$M$6) -> 15385.093 | G4: =IF($M$5*LN(G3)+$M$6<0,0,$M$5*LN(G3)+$M$6) -> 10876.43 | H4: =IF($M$5*LN(H3)+$M$6<0,0,$M$5*LN(H3)+$M$6) -> 7192.5841 | I4: =IF($M$5*LN(I3)+$M$6<0,0,$M$5*LN(I3)+$M$6) -> 4077.9368 | J4: =IF($M$5*LN(J3)+$M$6<0,0,$M$5*LN(J3)+$M$6) -> 1379.9066 | L4: Equation Inputs
B5: Revenue | D5: =D3*D4 -> 293902.79 | E5: =E3*E4 -> 317966.56 | F5: =F3*F4 -> 307701.86 | G5: =G3*G4 -> 271910.75 | H5: =H3*H4 -> 215777.52 | I5: =I3*I4 -> 142727.79 | J5: =J3*J4 -> 55196.262 | L5: a | M5: ='1. LOBF Estimator'!L25 -> -20205.213
L6: b | M6: ='1. LOBF Estimator'!M25 -> 75914.501
G46: `

Sheet 3. Cost Calculation
B2: Fixed Costs
B4: Item | C4: Name | D4: Description | E4: Cost
B5: 1 | C5: Insurance | D5: Business liability insurance | E5: 2500
B6: 2 | C6: Advertising | D6: Search engine marketing, newspaper ads | E6: 5000
B7: 3 | C7: Utilities | D7: Electrical, water, heating and cooling | E7: 2000
B8: 4 | C8: Building lease | D8: Cost of office | E8: 15000
B9: 5 | C9: Equipment | D9: Cost of production equipment | E9: 10000
B10: 6 | C10: Salary | D10: Owner salary | E10: 25000
B11: 7 | C11: Other | D11: Miscellaneous | E11: 1500
B12: 8
B13: 9
B14: 10
B15: Total fixed costs | E15: =SUM(E5:E14) -> 61000
B17: Variable Costs
B19: Item | C19: Name | D19: Description | E19: Cost per unit
B20: 1 | C20: Wicks | D20: Candle production | E20: 0.05
B21: 2 | C21: Wax | D21: Candle production | E21: 0.2
B22: 3 | C22: Jars and lids | D22: Candle production | E22: 0.5
B23: 4 | C23: Labels | D23: Candle production | E23: 0.1
B24: 5 | C24: Postage | D24: Candle distribution | E24: 1
B25: 6 | C25: Other | D25: Contingency for leakage | E25: 0.25
B26: 7
B27: 8
B28: 9
B29: 10
B30: Total variable costs (per unit) | E30: =SUM(E20:E29) -> 2.1

Sheet 4. Breakeven Analysis
B2: Breakeven Analysis
C4: 1 | D4: 2 | E4: 3 | F4: 4 | G4: 5 | H4: 6 | I4: 7
B5: Units Sold | C5: ='2b. Exponential LOBF'!D4 -> 30756.965 | D5: ='2b. Exponential LOBF'!E4 -> 20894.479 | E5: ='2b. Exponential LOBF'!F4 -> 14194.484 | F5: ='2b. Exponential LOBF'!G4 -> 9642.9001 | G5: ='2b. Exponential LOBF'!H4 -> 6550.821 | H5: ='2b. Exponential LOBF'!I4 -> 4450.2437 | I5: ='2b. Exponential LOBF'!J4 -> 3023.2347
B6: Total Variable Cost | C6: =C12*C5 -> 64589.626 | D6: =D12*D5 -> 43878.405 | E6: =E12*E5 -> 29808.416 | F6: =F12*F5 -> 20250.09 | G6: =G12*G5 -> 13756.724 | H6: =H12*H5 -> 9345.5119 | I6: =I12*I5 -> 6348.7929
B7: Total Fixed Cost | C7: ='3. Cost Calculation'!$E$15 -> 61000 | D7: ='3. Cost Calculation'!$E$15 -> 61000 | E7: ='3. Cost Calculation'!$E$15 -> 61000 | F7: ='3. Cost Calculation'!$E$15 -> 61000 | G7: ='3. Cost Calculation'!$E$15 -> 61000 | H7: ='3. Cost Calculation'!$E$15 -> 61000 | I7: ='3. Cost Calculation'!$E$15 -> 61000
B8: Total Cost | C8: =SUM(C6:C7) -> 125589.63 | D8: =SUM(D6:D7) -> 104878.41 | E8: =SUM(E6:E7) -> 90808.416 | F8: =SUM(F6:F7) -> 81250.09 | G8: =SUM(G6:G7) -> 74756.724 | H8: =SUM(H6:H7) -> 70345.512 | I8: =SUM(I6:I7) -> 67348.793
C10: 1 | D10: 2 | E10: 3 | F10: 4 | G10: 5 | H10: 6 | I10: 7
B11: Units Sold | C11: =C5 -> 30756.965 | D11: =D5 -> 20894.479 | E11: =E5 -> 14194.484 | F11: =F5 -> 9642.9001 | G11: =G5 -> 6550.821 | H11: =H5 -> 4450.2437 | I11: =I5 -> 3023.2347
B12: Variable Costs | C12: ='3. Cost Calculation'!$E$30 -> 2.1 | D12: ='3. Cost Calculation'!$E$30 -> 2.1 | E12: ='3. Cost Calculation'!$E$30 -> 2.1 | F12: ='3. Cost Calculation'!$E$30 -> 2.1 | G12: ='3. Cost Calculation'!$E$30 -> 2.1 | H12: ='3. Cost Calculation'!$E$30 -> 2.1 | I12: ='3. Cost Calculation'!$E$30 -> 2.1
B13: Fixed Costs / Unit | C13: ='3. Cost Calculation'!$E$15/'4. Breakeven Analysis'!C11 -> 1.9832906 | D13: ='3. Cost Calculation'!$E$15/'4. Breakeven Analysis'!D11 -> 2.9194315 | E13: ='3. Cost Calculation'!$E$15/'4. Breakeven Analysis'!E11 -> 4.2974441 | F13: ='3. Cost Calculation'!$E$15/'4. Breakeven Analysis'!F11 -> 6.3258977 | G13: ='3. Cost Calculation'!$E$15/'4. Breakeven Analysis'!G11 -> 9.3118099 | H13: ='3. Cost Calculation'!$E$15/'4. Breakeven Analysis'!H11 -> 13.707114 | I13: ='3. Cost Calculation'!$E$15/'4. Breakeven Analysis'!I11 -> 20.177064
B14: Breakeven Price | C14: =SUM(C12:C13) -> 4.0832906 | D14: =SUM(D12:D13) -> 5.0194315 | E14: =SUM(E12:E13) -> 6.3974441 | F14: =SUM(F12:F13) -> 8.4258977 | G14: =SUM(G12:G13) -> 11.41181 | H14: =SUM(H12:H13) -> 15.807114 | I14: =SUM(I12:I13) -> 22.277064
C16: 1 | D16: 2 | E16: 3 | F16: 4 | G16: 5 | H16: 6 | I16: 7
B17: Selling Price | C17: ='2b. Exponential LOBF'!D3 -> 10 | D17: ='2b. Exponential LOBF'!E3 -> 15 | E17: ='2b. Exponential LOBF'!F3 -> 20 | F17: ='2b. Exponential LOBF'!G3 -> 25 | G17: ='2b. Exponential LOBF'!H3 -> 30 | H17: ='2b. Exponential LOBF'!I3 -> 35 | I17: ='2b. Exponential LOBF'!J3 -> 40
B18: Variable Costs | C18: ='3. Cost Calculation'!$E$30 -> 2.1 | D18: ='3. Cost Calculation'!$E$30 -> 2.1 | E18: ='3. Cost Calculation'!$E$30 -> 2.1 | F18: ='3. Cost Calculation'!$E$30 -> 2.1 | G18: ='3. Cost Calculation'!$E$30 -> 2.1 | H18: ='3. Cost Calculation'!$E$30 -> 2.1 | I18: ='3. Cost Calculation'!$E$30 -> 2.1
B19: Total Fixed Cost | C19: ='3. Cost Calculation'!$E$15 -> 61000 | D19: ='3. Cost Calculation'!$E$15 -> 61000 | E19: ='3. Cost Calculation'!$E$15 -> 61000 | F19: ='3. Cost Calculation'!$E$15 -> 61000 | G19: ='3. Cost Calculation'!$E$15 -> 61000 | H19: ='3. Cost Calculation'!$E$15 -> 61000 | I19: ='3. Cost Calculation'!$E$15 -> 61000
B20: Breakeven Revenue | C20: =C19/(1-(C18/C17)) -> 77215.19 | D20: =D19/(1-(D18/D17)) -> 70930.233 | E20: =E19/(1-(E18/E17)) -> 68156.425 | F20: =F19/(1-(F18/F17)) -> 66593.886 | G20: =G19/(1-(G18/G17)) -> 65591.398 | H20: =H19/(1-(H18/H17)) -> 64893.617 | I20: =I19/(1-(I18/I17)) -> 64379.947
B21: Breakeven Units | C21: =ROUNDUP(C19/(C17-C18),0) -> 7722 | D21: =ROUNDUP(D19/(D17-D18),0) -> 4729 | E21: =ROUNDUP(E19/(E17-E18),0) -> 3408 | F21: =ROUNDUP(F19/(F17-F18),0) -> 2664 | G21: =ROUNDUP(G19/(G17-G18),0) -> 2187 | H21: =ROUNDUP(H19/(H17-H18),0) -> 1855 | I21: =ROUNDUP(I19/(I17-I18),0) -> 1610

Sheet 5. Gross Margin Analysis
B2: Gross Profit Analysis
C4: 1 | D4: 2 | E4: 3 | F4: 4 | G4: 5 | H4: 6 | I4: 7
B5: Units Sold | C5: ='2b. Exponential LOBF'!D4 -> 30756.965 | D5: ='2b. Exponential LOBF'!E4 -> 20894.479 | E5: ='2b. Exponential LOBF'!F4 -> 14194.484 | F5: ='2b. Exponential LOBF'!G4 -> 9642.9001 | G5: ='2b. Exponential LOBF'!H4 -> 6550.821 | H5: ='2b. Exponential LOBF'!I4 -> 4450.2437 | I5: ='2b. Exponential LOBF'!J4 -> 3023.2347
B6: Price | C6: ='4. Breakeven Analysis'!C17 -> 10 | D6: ='4. Breakeven Analysis'!D17 -> 15 | E6: ='4. Breakeven Analysis'!E17 -> 20 | F6: ='4. Breakeven Analysis'!F17 -> 25 | G6: ='4. Breakeven Analysis'!G17 -> 30 | H6: ='4. Breakeven Analysis'!H17 -> 35 | I6: ='4. Breakeven Analysis'!I17 -> 40
B7: Revenue | C7: =C5*C6 -> 307569.65 | D7: =D5*D6 -> 313417.18 | E7: =E5*E6 -> 283889.68 | F7: =F5*F6 -> 241072.5 | G7: =G5*G6 -> 196524.63 | H7: =H5*H6 -> 155758.53 | I7: =I5*I6 -> 120929.39
B8: Variable Costs | C8: =C5*'3. Cost Calculation'!$E$30 -> 64589.626 | D8: =D5*'3. Cost Calculation'!$E$30 -> 43878.405 | E8: =E5*'3. Cost Calculation'!$E$30 -> 29808.416 | F8: =F5*'3. Cost Calculation'!$E$30 -> 20250.09 | G8: =G5*'3. Cost Calculation'!$E$30 -> 13756.724 | H8: =H5*'3. Cost Calculation'!$E$30 -> 9345.5119 | I8: =I5*'3. Cost Calculation'!$E$30 -> 6348.7929
B9: Fixed Costs | C9: ='3. Cost Calculation'!$E$15 -> 61000 | D9: ='3. Cost Calculation'!$E$15 -> 61000 | E9: ='3. Cost Calculation'!$E$15 -> 61000 | F9: ='3. Cost Calculation'!$E$15 -> 61000 | G9: ='3. Cost Calculation'!$E$15 -> 61000 | H9: ='3. Cost Calculation'!$E$15 -> 61000 | I9: ='3. Cost Calculation'!$E$15 -> 61000
B10: Total Costs | C10: =SUM(C8:C9) -> 125589.63 | D10: =SUM(D8:D9) -> 104878.41 | E10: =SUM(E8:E9) -> 90808.416 | F10: =SUM(F8:F9) -> 81250.09 | G10: =SUM(G8:G9) -> 74756.724 | H10: =SUM(H8:H9) -> 70345.512 | I10: =SUM(I8:I9) -> 67348.793
B11: Gross Profit | C11: =C7-C10 -> 181980.02 | D11: =D7-D10 -> 208538.77 | E11: =E7-E10 -> 193081.26 | F11: =F7-F10 -> 159822.41 | G11: =G7-G10 -> 121767.91 | H11: =H7-H10 -> 85413.019 | I11: =I7-I10 -> 53580.595
