Workbook

Sheet 0. Document Details
B2: Product Business Case v1.0
B4: Document details
B5: Document owner | C5: Joe Bloggs
B6: Document version | C6: 1.0
B7: Last updated | C7: =TODAY() -> 45423

Sheet 1. Checklist
B2: Tasks
C4: Task | D4: Frequency | E4: Current Status | F4: Completion Date | G4: Signed Off
B5: 1
B6: 2
B7: 3
B8: 4
B9: 5
B10: 6
B11: 7
B12: 8
B13: 9
B14: 10
B15: 11
B16: 12

Sheet 2. Product Overview
B2: Product Overview
B4: 1. Key Project Details | E4: 2. Project Description
B5: Product Name | C5: [Example Product] | E5: Product Manager
B6: Product Description | E6: Funding Source
B7: Target Customer(s) | E7: Estimated Benefits
B8: Customer Need(s) | E8: Estimated Budget
B10: 3. Product Scope | E10: 4. Schedule and Milestones
B11: 3.1 Inclusions | E11: 4.1 Project Timeline
E12: Soonest Possible Start: | G12: Soonest Possible End:
E13: Latest Possible Start: | G13: Latest Possible End:
E14: 4.2 Key Milestones
E15: Milestone | G15: Planned Start | H15: Actual Start | I15: Planned End | J15: Actual End
B17: 3.2 Exclusions
B24: 5. Risks of Proposed Product (if applicable) | E24: 6. Completion Criteria
B25: 5.1 Known Risks

Sheet 3a. Unit Economics - Revenue
B2: =CONCATENATE('2. Product Overview'!C5, " Revenue") -> [Example Product] Revenue
C4: Year 1 | D4: Year 2 | E4: Year 3 | F4: Year 4 | G4: Year 5 | H4: Year 6 | I4: Year 7
B5: Selling Price | C5: 15 | D5: =C5 -> 15 | E5: =D5 -> 15 | F5: =E5 -> 15 | G5: =F5 -> 15 | H5: =G5 -> 15 | I5: =H5 -> 15
B6: Quantity Sold | C6: 1000 | D6: =C6*2 -> 2000 | E6: =D6*2 -> 4000 | F6: =E6*2 -> 8000 | G6: =F6*2 -> 16000 | H6: =G6*2 -> 32000 | I6: =H6*2 -> 64000
B7: Revenue | C7: =C5*C6 -> 15000 | D7: =D5*D6 -> 30000 | E7: =E5*E6 -> 60000 | F7: =F5*F6 -> 120000 | G7: =G5*G6 -> 240000 | H7: =H5*H6 -> 480000 | I7: =I5*I6 -> 960000

Sheet 3b. Unit Economics - Costs
B2: =CONCATENATE('2. Product Overview'!C5," Costs") -> [Example Product] Costs
B4: Fixed Costs
B6: Item | C6: Name | D6: Description | E6: Cost
B7: 1 | E7: 2500
B8: 2 | E8: 5000
B9: 3 | E9: 2000
B10: 4 | E10: 15000
B11: 5 | E11: 10000
B12: 6 | E12: 25000
B13: 7 | E13: 1500
B14: 8
B15: 9
B16: 10
B17: Total fixed costs | E17: =SUM(E7:E16) -> 61000
B19: Variable Costs
B21: Item | C21: Name | D21: Description | E21: Cost per unit
B22: 1 | E22: 0.05
B23: 2 | E23: 0.2
B24: 3 | E24: 0.5
B25: 4 | E25: 0.1
B26: 5 | E26: 1
B27: 6 | E27: 0.25
B28: 7
B29: 8
B30: 9
B31: 10
B32: Total variable costs (per unit) | E32: =SUM(E22:E31) -> 2.1

Sheet 3c. Unit Economics - Breakeven
B2: =CONCATENATE('2. Product Overview'!C5," Breakeven") -> [Example Product] Breakeven
C4: Year 1 | D4: Year 2 | E4: Year 3 | F4: Year 4 | G4: Year 5 | H4: Year 6 | I4: Year 7
B5: Selling Price | C5: ='3a. Unit Economics - Revenue'!C5 -> 15 | D5: ='3a. Unit Economics - Revenue'!D5 -> 15 | E5: ='3a. Unit Economics - Revenue'!E5 -> 15 | F5: ='3a. Unit Economics - Revenue'!F5 -> 15 | G5: ='3a. Unit Economics - Revenue'!G5 -> 15 | H5: ='3a. Unit Economics - Revenue'!H5 -> 15 | I5: ='3a. Unit Economics - Revenue'!I5 -> 15
B6: Quantity Sold | C6: ='3a. Unit Economics - Revenue'!C6 -> 1000 | D6: ='3a. Unit Economics - Revenue'!D6 -> 2000 | E6: ='3a. Unit Economics - Revenue'!E6 -> 4000 | F6: ='3a. Unit Economics - Revenue'!F6 -> 8000 | G6: ='3a. Unit Economics - Revenue'!G6 -> 16000 | H6: ='3a. Unit Economics - Revenue'!H6 -> 32000 | I6: ='3a. Unit Economics - Revenue'!I6 -> 64000
B7: Revenue | C7: =C5*C6 -> 15000 | D7: =D5*D6 -> 30000 | E7: =E5*E6 -> 60000 | F7: =F5*F6 -> 120000 | G7: =G5*G6 -> 240000 | H7: =H5*H6 -> 480000 | I7: =I5*I6 -> 960000
C9: Year 1 | D9: Year 2 | E9: Year 3 | F9: Year 4 | G9: Year 5 | H9: Year 6 | I9: Year 7
B10: Fixed Costs | C10: ='3b. Unit Economics - Costs'!$E$17 -> 61000 | D10: ='3b. Unit Economics - Costs'!$E$17 -> 61000 | E10: ='3b. Unit Economics - Costs'!$E$17 -> 61000 | F10: ='3b. Unit Economics - Costs'!$E$17 -> 61000 | G10: ='3b. Unit Economics - Costs'!$E$17 -> 61000 | H10: ='3b. Unit Economics - Costs'!$E$17 -> 61000 | I10: ='3b. Unit Economics - Costs'!$E$17 -> 61000
B11: Variable Costs | C11: =C6*'3b. Unit Economics - Costs'!$E$32 -> 2100 | D11: =D6*'3b. Unit Economics - Costs'!$E$32 -> 4200 | E11: =E6*'3b. Unit Economics - Costs'!$E$32 -> 8400 | F11: =F6*'3b. Unit Economics - Costs'!$E$32 -> 16800 | G11: =G6*'3b. Unit Economics - Costs'!$E$32 -> 33600 | H11: =H6*'3b. Unit Economics - Costs'!$E$32 -> 67200 | I11: =I6*'3b. Unit Economics - Costs'!$E$32 -> 134400
B12: Total Cost | C12: =SUM(C10:C11) -> 63100 | D12: =SUM(D10:D11) -> 65200 | E12: =SUM(E10:E11) -> 69400 | F12: =SUM(F10:F11) -> 77800 | G12: =SUM(G10:G11) -> 94600 | H12: =SUM(H10:H11) -> 128200 | I12: =SUM(I10:I11) -> 195400
C14: Year 1 | D14: Year 2 | E14: Year 3 | F14: Year 4 | G14: Year 5 | H14: Year 6 | I14: Year 7
B15: Total Revenue | C15: =C7 -> 15000 | D15: =D7 -> 30000 | E15: =E7 -> 60000 | F15: =F7 -> 120000 | G15: =G7 -> 240000 | H15: =H7 -> 480000 | I15: =I7 -> 960000
B16: Total Costs | C16: =C12 -> 63100 | D16: =D12 -> 65200 | E16: =E12 -> 69400 | F16: =F12 -> 77800 | G16: =G12 -> 94600 | H16: =H12 -> 128200 | I16: =I12 -> 195400
B17: Gross Profit | C17: =C15-C16 -> -48100 | D17: =D15-D16 -> -35200 | E17: =E15-E16 -> -9400 | F17: =F15-F16 -> 42200 | G17: =G15-G16 -> 145400 | H17: =H15-H16 -> 351800 | I17: =I15-I16 -> 764600
B18: Gross Profit Margin | C18: =C17/C15 -> -3.2066667 | D18: =D17/D15 -> -1.1733333 | E18: =E17/E15 -> -0.15666667 | F18: =F17/F15 -> 0.35166667 | G18: =G17/G15 -> 0.60583333 | H18: =H17/H15 -> 0.73291667 | I18: =I17/I15 -> 0.79645833
C20: Year 1 | D20: Year 2 | E20: Year 3 | F20: Year 4 | G20: Year 5 | H20: Year 6 | I20: Year 7
B21: Cumulative Breakeven | C21: =SUM($C$7:C7)-SUM($C$12:C12) -> -48100 | D21: =SUM($C$7:D7)-SUM($C$12:D12) -> -83300 | E21: =SUM($C$7:E7)-SUM($C$12:E12) -> -92700 | F21: =SUM($C$7:F7)-SUM($C$12:F12) -> -50500 | G21: =SUM($C$7:G7)-SUM($C$12:G12) -> 94900 | H21: =SUM($C$7:H7)-SUM($C$12:H12) -> 446700 | I21: =SUM($C$7:I7)-SUM($C$12:I12) -> 1211300
B22: Breakeven Price | C22: =(C10/C6)+'3b. Unit Economics - Costs'!$E$32 -> 63.1 | D22: =(D10/D6)+'3b. Unit Economics - Costs'!$E$32 -> 32.6 | E22: =(E10/E6)+'3b. Unit Economics - Costs'!$E$32 -> 17.35 | F22: =(F10/F6)+'3b. Unit Economics - Costs'!$E$32 -> 9.725 | G22: =(G10/G6)+'3b. Unit Economics - Costs'!$E$32 -> 5.9125 | H22: =(H10/H6)+'3b. Unit Economics - Costs'!$E$32 -> 4.00625 | I22: =(I10/I6)+'3b. Unit Economics - Costs'!$E$32 -> 3.053125
B23: Breakeven Units | C23: =C10/('3c. Unit Economics - Breakeven'!C5-'3b. Unit Economics - Costs'!$E$32) -> 4728.6822 | D23: =D10/('3c. Unit Economics - Breakeven'!D5-'3b. Unit Economics - Costs'!$E$32) -> 4728.6822 | E23: =E10/('3c. Unit Economics - Breakeven'!E5-'3b. Unit Economics - Costs'!$E$32) -> 4728.6822 | F23: =F10/('3c. Unit Economics - Breakeven'!F5-'3b. Unit Economics - Costs'!$E$32) -> 4728.6822 | G23: =G10/('3c. Unit Economics - Breakeven'!G5-'3b. Unit Economics - Costs'!$E$32) -> 4728.6822 | H23: =H10/('3c. Unit Economics - Breakeven'!H5-'3b. Unit Economics - Costs'!$E$32) -> 4728.6822 | I23: =I10/('3c. Unit Economics - Breakeven'!I5-'3b. Unit Economics - Costs'!$E$32) -> 4728.6822

Sheet 4. Launch Calendar
B2: =CONCATENATE("Launch Calendar for ",'2. Product Overview'!C5) -> Launch Calendar for [Example Product]
B4: Milestone | D4: Owner | E4: Due Date | F4: Status | G4: Wk 1 | H4: Wk 2 | I4: Wk 3 | J4: Wk 4 | K4: Wk 5 | L4: Wk 6 | M4: Wk 7 | N4: Wk 8 | O4: Wk 9 | P4: Wk10
B5: Phase 1: Describe phase here
B6: 1.1 | C6: Milestone
B7: 1.2 | C7: Milestone
B8: 1.3 | C8: Milestone
B9: Phase 2: Describe phase here
B10: 2.1 | C10: Milestone
B11: 2.2 | C11: Milestone
B12: 2.3 | C12: Milestone
B13: 2.4 | C13: Milestone
B14: Phase 3: Describe phase here
B15: 3.1 | C15: Milestone
B16: 3.2 | C16: Milestone
B17: 3.3 | C17: Milestone
